incidentsBugDSI/__init__.py
incidentsBugDSI/bugReports.py
incidentsBugDSI-0.4.dist-info/LICENSE
incidentsBugDSI-0.4.dist-info/METADATA
incidentsBugDSI-0.4.dist-info/WHEEL
incidentsBugDSI-0.4.dist-info/top_level.txt
incidentsBugDSI-0.4.dist-info/RECORD
