Metadata-Version: 2.1
Name: incidentsBugDSI
Version: 0.4
Summary: Gestión de incidencias de tipo bug
Home-page: https://dsinno@bitbucket.org/rpa-s/libreriagestionincidenciastipobug.git
Author: DSI.
Author-email: jairo@dsinno.io
License: MIT
License-File: LICENSE
Requires-Dist: pika
